kiqpoliveserver/__init__.py
kiqpoliveserver/cli.py
kiqpoliveserver/handlers.py
kiqpoliveserver/server.py
kiqpoliveserver/watcher.py
kiqpolivereload-0.0.9.dist-info/LICENSE
kiqpolivereload-0.0.9.dist-info/METADATA
kiqpolivereload-0.0.9.dist-info/WHEEL
kiqpolivereload-0.0.9.dist-info/top_level.txt
kiqpolivereload-0.0.9.dist-info/RECORD
